q_alchemy/__init__.py
q_alchemy/initialize.py
q_alchemy/pennylane_integration.py
q_alchemy/pyarrow_data.py
q_alchemy/qiskit_integration.py
q_alchemy/utils.py
q_alchemy_sdk_py-0.2.24.dist-info/METADATA
q_alchemy_sdk_py-0.2.24.dist-info/WHEEL
q_alchemy_sdk_py-0.2.24.dist-info/entry_points.txt
q_alchemy_sdk_py-0.2.24.dist-info/licenses/LICENSE
q_alchemy_sdk_py-0.2.24.dist-info/RECORD
