Metadata-Version: 2.1
Name: q-alchemy-sdk-py
Version: 0.2.24
Author-Email: Carsten Blank <blank@data-cybernetics.com>
License: Apache
Requires-Python: <4,>=3.11
Requires-Dist: pydantic>=2.6.4
Requires-Dist: httpx<1.0.0,>=0.25.0
Requires-Dist: tenacity>=8.2.3
Requires-Dist: pinexq-client>=0.9.2.20250828.47
Requires-Dist: tqdm
Requires-Dist: pyarrow>=19.0.1
Provides-Extra: qiskit
Requires-Dist: qiskit[qasm3-import]>=1.2.0; extra == "qiskit"
Provides-Extra: pennylane
Requires-Dist: pennylane>=0.42.0; extra == "pennylane"
Requires-Dist: openqasm3[parser]; extra == "pennylane"
Requires-Dist: pennylane-qiskit>=0.42.0; extra == "pennylane"
Provides-Extra: examples
Requires-Dist: qiskit>=1.2.0; extra == "examples"
Requires-Dist: pennylane>=0.42.0; extra == "examples"
Requires-Dist: pennylane-qiskit>=0.42.0; extra == "examples"
Requires-Dist: openqasm3[parser]; extra == "examples"
Requires-Dist: qutip; extra == "examples"
Requires-Dist: pylatexenc; extra == "examples"
Requires-Dist: qiskit_experiments; extra == "examples"
Requires-Dist: qiskit_aer; extra == "examples"
Requires-Dist: jupyter; extra == "examples"
Requires-Dist: matplotlib; extra == "examples"
Requires-Dist: pandas; extra == "examples"
Requires-Dist: scikit-learn; extra == "examples"
